[
 {
  "table":"DDLXSRC",
  "data":
  [
   {
    "DDLXNAME":"/IIE/C_MEMBERSHIPTYPES",
    "VERSION":"A",
    "CHANGED_BY":"SAP_CUSTOMER",
    "CHANGED_ON":"2024-08-10",
    "CHANGED_AT":"08:38:49",
    "UUID":"7A5E3FC8EFE51EDF95DE7EDC356DEBCE",
    "ABAP_LANGUAGE_VERSION":"5"
   }
  ]
 },
 {
  "table":"DDLXSRCT",
  "data":
  [
   {
    "DDLXNAME":"/IIE/C_MEMBERSHIPTYPES",
    "VERSION":"A",
    "LANGUAGE":"E",
    "DESCRIPTION":"Metadata Extension for /IIE/C_MembershipTypes"
   }
  ]
 },
 {
  "table":"DDLXSRC_SRC",
  "data":
  [
   {
    "DDLXNAME":"/IIE/C_MEMBERSHIPTYPES",
    "VERSION":"A",
    "UUID":"",
    "SOURCE":"@Metadata.layer: #CUSTOMER\r\n@UI: {\r\n  headerInfo: {\r\n    typeName: 'MembershipTypes', \r\n    typeNamePlural: 'MembershipTypess', \r\n    title: {\r\n      type: #STANDARD, \r\n      label: 'Membership types', \r\n      value: 'Membershiptype'\r\n    }\r\n  }\r\n}\r\nannotate view /IIE/C_MembershipTypes with\r\n{\r\n  @UI.identification: [ {\r\n    position: 1 \r\n  } ]\r\n  @UI.lineItem: [ {\r\n    position: 1 \r\n  } ]\r\n  @UI.facet: [ {\r\n    id: '/IIE/I_MembershipTypes', \r\n    purpose: #STANDARD, \r\n    type: #IDENTIFICATION_REFERENCE, \r\n    label: 'Membership types', \r\n    position: 1 \r\n  }, \r\n  {\r\n    id: '/IIE/I_MembershipTypesText', \r\n    type: #LINEITEM_REFERENCE, \r\n    label: 'Membership types Text', \r\n    position: 2 , \r\n    targetElement: '_MembershipTypesText'\r\n  } ]\r\n  Membershiptype;\r\n  \r\n  @UI.identification: [ {\r\n    hidden: true, \r\n    position: 2 \r\n  } ]\r\n  @UI.lineItem: [ {\r\n    position: 2 \r\n  } ]\r\n  Description;\r\n}"
   }
  ]
 },
 {
  "table":"DDLX_RT_DATA",
  "data":
  [
   {
    "DDLXNAME":"/IIE/C_MEMBERSHIPTYPES",
    "ELEMENT":"",
    "NAME":"UI.HEADERINFO.TITLE.LABEL",
    "ELEMENT_TYPE":"N",
    "VALUE":"'Membership types'"
   },
   {
    "DDLXNAME":"/IIE/C_MEMBERSHIPTYPES",
    "ELEMENT":"",
    "NAME":"UI.HEADERINFO.TITLE.TYPE",
    "ELEMENT_TYPE":"N",
    "VALUE":"#STANDARD"
   },
   {
    "DDLXNAME":"/IIE/C_MEMBERSHIPTYPES",
    "ELEMENT":"",
    "NAME":"UI.HEADERINFO.TITLE.VALUE",
    "ELEMENT_TYPE":"N",
    "VALUE":"'Membershiptype'"
   },
   {
    "DDLXNAME":"/IIE/C_MEMBERSHIPTYPES",
    "ELEMENT":"",
    "NAME":"UI.HEADERINFO.TYPENAME",
    "ELEMENT_TYPE":"N",
    "VALUE":"'MembershipTypes'"
   },
   {
    "DDLXNAME":"/IIE/C_MEMBERSHIPTYPES",
    "ELEMENT":"",
    "NAME":"UI.HEADERINFO.TYPENAMEPLURAL",
    "ELEMENT_TYPE":"N",
    "VALUE":"'MembershipTypess'"
   },
   {
    "DDLXNAME":"/IIE/C_MEMBERSHIPTYPES",
    "ELEMENT":"DESCRIPTION",
    "NAME":"UI.IDENTIFICATION$1$.HIDDEN",
    "ELEMENT_TYPE":"S",
    "VALUE":"true"
   },
   {
    "DDLXNAME":"/IIE/C_MEMBERSHIPTYPES",
    "ELEMENT":"DESCRIPTION",
    "NAME":"UI.IDENTIFICATION$1$.POSITION",
    "ELEMENT_TYPE":"S",
    "VALUE":"2"
   },
   {
    "DDLXNAME":"/IIE/C_MEMBERSHIPTYPES",
    "ELEMENT":"DESCRIPTION",
    "NAME":"UI.LINEITEM$1$.POSITION",
    "ELEMENT_TYPE":"S",
    "VALUE":"2"
   },
   {
    "DDLXNAME":"/IIE/C_MEMBERSHIPTYPES",
    "ELEMENT":"MEMBERSHIPTYPE",
    "NAME":"UI.FACET$1$.ID",
    "ELEMENT_TYPE":"S",
    "VALUE":"'/IIE/I_MembershipTypes'"
   },
   {
    "DDLXNAME":"/IIE/C_MEMBERSHIPTYPES",
    "ELEMENT":"MEMBERSHIPTYPE",
    "NAME":"UI.FACET$1$.LABEL",
    "ELEMENT_TYPE":"S",
    "VALUE":"'Membership types'"
   },
   {
    "DDLXNAME":"/IIE/C_MEMBERSHIPTYPES",
    "ELEMENT":"MEMBERSHIPTYPE",
    "NAME":"UI.FACET$1$.POSITION",
    "ELEMENT_TYPE":"S",
    "VALUE":"1"
   },
   {
    "DDLXNAME":"/IIE/C_MEMBERSHIPTYPES",
    "ELEMENT":"MEMBERSHIPTYPE",
    "NAME":"UI.FACET$1$.PURPOSE",
    "ELEMENT_TYPE":"S",
    "VALUE":"#STANDARD"
   },
   {
    "DDLXNAME":"/IIE/C_MEMBERSHIPTYPES",
    "ELEMENT":"MEMBERSHIPTYPE",
    "NAME":"UI.FACET$1$.TYPE",
    "ELEMENT_TYPE":"S",
    "VALUE":"#IDENTIFICATION_REFERENCE"
   },
   {
    "DDLXNAME":"/IIE/C_MEMBERSHIPTYPES",
    "ELEMENT":"MEMBERSHIPTYPE",
    "NAME":"UI.FACET$2$.ID",
    "ELEMENT_TYPE":"S",
    "VALUE":"'/IIE/I_MembershipTypesText'"
   },
   {
    "DDLXNAME":"/IIE/C_MEMBERSHIPTYPES",
    "ELEMENT":"MEMBERSHIPTYPE",
    "NAME":"UI.FACET$2$.LABEL",
    "ELEMENT_TYPE":"S",
    "VALUE":"'Membership types Text'"
   },
   {
    "DDLXNAME":"/IIE/C_MEMBERSHIPTYPES",
    "ELEMENT":"MEMBERSHIPTYPE",
    "NAME":"UI.FACET$2$.POSITION",
    "ELEMENT_TYPE":"S",
    "VALUE":"2"
   },
   {
    "DDLXNAME":"/IIE/C_MEMBERSHIPTYPES",
    "ELEMENT":"MEMBERSHIPTYPE",
    "NAME":"UI.FACET$2$.TARGETELEMENT",
    "ELEMENT_TYPE":"S",
    "VALUE":"'_MembershipTypesText'"
   },
   {
    "DDLXNAME":"/IIE/C_MEMBERSHIPTYPES",
    "ELEMENT":"MEMBERSHIPTYPE",
    "NAME":"UI.FACET$2$.TYPE",
    "ELEMENT_TYPE":"S",
    "VALUE":"#LINEITEM_REFERENCE"
   },
   {
    "DDLXNAME":"/IIE/C_MEMBERSHIPTYPES",
    "ELEMENT":"MEMBERSHIPTYPE",
    "NAME":"UI.IDENTIFICATION$1$.POSITION",
    "ELEMENT_TYPE":"S",
    "VALUE":"1"
   },
   {
    "DDLXNAME":"/IIE/C_MEMBERSHIPTYPES",
    "ELEMENT":"MEMBERSHIPTYPE",
    "NAME":"UI.LINEITEM$1$.POSITION",
    "ELEMENT_TYPE":"S",
    "VALUE":"1"
   }
  ]
 },
 {
  "table":"DDLX_RT_DATA_T",
  "data":
  [
   {
    "DDLXNAME":"/IIE/C_MEMBERSHIPTYPES",
    "DDLANGUAGE":"E",
    "ELEMENT":"",
    "NAME":"UI.HEADERINFO.TITLE.LABEL",
    "TEXT":"Membership types"
   },
   {
    "DDLXNAME":"/IIE/C_MEMBERSHIPTYPES",
    "DDLANGUAGE":"E",
    "ELEMENT":"",
    "NAME":"UI.HEADERINFO.TYPENAME",
    "TEXT":"MembershipTypes"
   },
   {
    "DDLXNAME":"/IIE/C_MEMBERSHIPTYPES",
    "DDLANGUAGE":"E",
    "ELEMENT":"",
    "NAME":"UI.HEADERINFO.TYPENAMEPLURAL",
    "TEXT":"MembershipTypess"
   },
   {
    "DDLXNAME":"/IIE/C_MEMBERSHIPTYPES",
    "DDLANGUAGE":"E",
    "ELEMENT":"MEMBERSHIPTYPE",
    "NAME":"UI.FACET$1$.LABEL",
    "TEXT":"Membership types"
   },
   {
    "DDLXNAME":"/IIE/C_MEMBERSHIPTYPES",
    "DDLANGUAGE":"E",
    "ELEMENT":"MEMBERSHIPTYPE",
    "NAME":"UI.FACET$2$.LABEL",
    "TEXT":"Membership types Text"
   }
  ]
 },
 {
  "table":"DDLX_RT_HEADER",
  "data":
  [
   {
    "DDLXNAME":"/IIE/C_MEMBERSHIPTYPES",
    "EXTENDED_ARTIFACT":"/IIE/C_MEMBERSHIPTYPES",
    "VARIANT":"",
    "LAYER":5500,
    "DT_UUID":"7A5E3FC8EFE51EDF95DE7EDC356DEBCE",
    "RT_HASH":"298B3785AE0129B3C2C80BB31C48542C19FAC21F",
    "GEN_VERSION":"0",
    "TYPE":"0"
   }
  ]
 },
 {
  "table":"TADIR",
  "data":
  [
   {
    "PGMID":"R3TR",
    "OBJECT":"DDLX",
    "OBJ_NAME":"/IIE/C_MEMBERSHIPTYPES",
    "KORRNUM":"",
    "SRCSYSTEM":"...",
    "AUTHOR":"SAP_CUSTOMER",
    "SRCDEP":"",
    "DEVCLASS":"/IIE/CLBMAN_CDS",
    "GENFLAG":"",
    "EDTFLAG":"",
    "CPROJECT":" S",
    "MASTERLANG":"E",
    "VERSID":"",
    "PAKNOCHECK":"",
    "OBJSTABLTY":"",
    "COMPONENT":"/IIE/CLBMAN",
    "CRELEASE":"100",
    "DELFLAG":"",
    "TRANSLTTXT":"",
    "CREATED_ON":"2024-08-09",
    "CHECK_DATE":"2024-08-09",
    "CHECK_CFG":""
   }
  ]
 }
]